TEST_ETAE/__init__.py
TEST_ETAE/main.py
TEST_ETAE/externals/__init__.py
TEST_ETAE/externals/my.py
TEST_ETAE-0.0.12.dist-info/METADATA
TEST_ETAE-0.0.12.dist-info/WHEEL
TEST_ETAE-0.0.12.dist-info/top_level.txt
TEST_ETAE-0.0.12.dist-info/RECORD
