Metadata-Version: 2.1
Name: TEST-ETAE
Version: 0.0.12
Summary: A temp upload for ETA prediction
Home-page: UNKNOWN
License: UNKNOWN
Platform: UNKNOWN
Classifier: Programming Language :: Python :: 3
Classifier: License :: OSI Approved :: MIT License
Classifier: Operating System :: OS Independent
